steggi/__init__.py
steggi/__main__.py
steggi/combiners.py
steggi/converters.py
steggi/extractors.py
steggi/steggi.py
steggi-0.2.1.dist-info/entry_points.txt
steggi-0.2.1.dist-info/LICENSE
steggi-0.2.1.dist-info/WHEEL
steggi-0.2.1.dist-info/METADATA
steggi-0.2.1.dist-info/RECORD
